ideascale/__init__.py
ideascale/excelformat.py
ideascale/markdown.py
ideascale/totsv.py
ideascale-0.1.9.dist-info/METADATA
ideascale-0.1.9.dist-info/WHEEL
ideascale-0.1.9.dist-info/top_level.txt
ideascale-0.1.9.dist-info/RECORD
