Metadata-Version: 2.1
Name: ideascale
Version: 0.1.9
Summary: This package is for ideascale
Author: Tien Nguyen
Author-email: tiennguyenhotel97@gmail.com
License: UNKNOWN
Keywords: python,excel
Platform: UNKNOWN
Classifier: Development Status :: 1 - Planning
Classifier: Intended Audience :: Developers
Classifier: Programming Language :: Python :: 3
Classifier: Operating System :: Unix
Classifier: Operating System :: MacOS :: MacOS X
Classifier: Operating System :: Microsoft :: Windows
Requires-Dist: pandas
Requires-Dist: xlsxwriter
Requires-Dist: openpyxl
